wagtail_redisearch/__init__.py
wagtail_redisearch/apps.py
wagtail_redisearch/backend.py
wagtail_redisearch-0.4.0.dist-info/LICENSE
wagtail_redisearch-0.4.0.dist-info/WHEEL
wagtail_redisearch-0.4.0.dist-info/METADATA
wagtail_redisearch-0.4.0.dist-info/RECORD
