Metadata-Version: 2.1
Name: wagtail-redisearch
Version: 0.4.0
Summary: A Django app to use RediSearch as a search backend in Wagtail.
Home-page: https://github.com/TommasoAmici/wagtail-redisearch
License: MIT
Author: Tommaso Amici
Author-email: me@tommasoamici.com
Requires-Python: >=3.7,<4.0
Classifier: Development Status :: 4 - Beta
Classifier: Framework :: Django
Classifier: Framework :: Django :: 3.2
Classifier: Framework :: Django :: 4
Classifier: Framework :: Wagtail
Classifier: Framework :: Wagtail :: 2
Classifier: License :: OSI Approved :: MIT License
Classifier: Programming Language :: Python :: 3
Classifier: Programming Language :: Python :: 3.10
Classifier: Programming Language :: Python :: 3.7
Classifier: Programming Language :: Python :: 3.8
Classifier: Programming Language :: Python :: 3.9
Requires-Dist: Django (>=3.2,<5.0)
Requires-Dist: redis (>=4.0.0,<5.0.0)
Requires-Dist: wagtail (>=2.15,<3.0)
Project-URL: Repository, https://github.com/TommasoAmici/wagtail-redisearch
